{
  "survey_id": "baffc0d7-3010-42ba-88a2-83693682cc9a",
  "exported_at": "2025-12-09_14-27-20",
  "answers": {
    "Q1": {
      "question": "Unapoteza mavuno kiasi gani kutokana na funza wa jeshi vamizi (FAW)? Tafadhali fikiria misimu mitatu iliyopita. (Asilimia au magunia kwa ekari ni sawa.)",
      "answer": "[BLANK_AUDIO]",
      "audio": [
        { "file": "voice_baffc0d7-3010-42ba-88a2-83693682cc9a_Q1_20251209_111503.wav" }
      ]
    },
    "Q2": {
      "question": "Ikiwa ungeweza kuvuna siku 10 mapema, ungekuwa tayari kupunguza mavuno kiasi gani? (Asilimia au magunia kwa ekari.)",
      "answer": "[speaking in foreign language]",
      "audio": [
        { "file": "voice_baffc0d7-3010-42ba-88a2-83693682cc9a_Q2_20251209_111644.wav" }
      ]
    },
    "Q3": {
      "question": "Ni kiwango gani cha uharibifu wa wadudu au magonjwa kingekufanya uache kutumia aina yako ya sasa ya mahindi na ubadilishe kwenda aina mpya? (Toa kigezo wazi, kwa mfano: asilimia ya mimea au masikio yaliyoharibika, au kiwango cha ukali.)",
      "answer": "[NON-ENGLISH SPEECH]",
      "audio": [
        { "file": "voice_baffc0d7-3010-42ba-88a2-83693682cc9a_Q3_20251209_111802.wav" },
        { "file": "voice_baffc0d7-3010-42ba-88a2-83693682cc9a_Q3_20251209_111839.wav" }
      ]
    },
    "Q4": {
      "question": "Ungetarajia nini kutoka kwa aina mpya ya mahindi ili kuchukua nafasi ya ile unayolima sasa? Tafadhali toa maelezo kwa undani kadiri inavyowezekana (kwa mfano, muda wa kukomaa (DTM), uvumilivu wa FAW, uvumilivu wa ukame katika hatua fulani, mavuno ya kawaida).",
      "answer": "[Spanish]",
      "audio": [
        { "file": "voice_baffc0d7-3010-42ba-88a2-83693682cc9a_Q4_20251209_111912.wav" },
        { "file": "voice_baffc0d7-3010-42ba-88a2-83693682cc9a_Q4_20251209_111934.wav" }
      ]
    },
    "Q5": {
      "question": "Katika mwaka mbaya, ni mavuno madogo kiasi gani ambayo ungeyakubali na bado ukapande mahindi haya tena msimu unaofuata? (Asilimia ya mavuno ya kawaida au magunia kwa ekari.)",
      "answer": "(speaking in foreign language)",
      "audio": [
        { "file": "voice_baffc0d7-3010-42ba-88a2-83693682cc9a_Q5_20251209_112231.wav" },
        { "file": "voice_baffc0d7-3010-42ba-88a2-83693682cc9a_Q5_20251209_112341.wav" }
      ]
    },
    "Q6": {
      "question": "Ni kipindi gani katika msimu ambapo ukame unaathiri mazao yako kwa kiwango kikubwa zaidi? Ni wakati gani wa ukame ambao ni mgumu zaidi kwako? (Kwa mfano, kabla ya kutoa maua, wakati wa kutoa maua/kuchanua, kujaza punje, kabla ya kuvuna.)",
      "answer": "[BLANK_AUDIO]",
      "audio": [
        { "file": "voice_baffc0d7-3010-42ba-88a2-83693682cc9a_Q6_20251209_112518.wav" }
      ]
    },
    "Start": {
      "question": "Anza",
      "answer": ""
    }
  },
  "followups": {
    "Q1": [
      { "question": "{\"analysis\":\"Mauzo ya mavuno FAW hazipoชัดเจน.\\nExpected answer\":\"FAW yield loss avg over last 3 seasons (% or bags/acre). Note variability if highटीसी.\\nfollow-up question\":\"Unaweza kutokeza kiasi gani kwa asilimia au magunia kwa ekari kwa misimu mitatu iliyopita kuhusu FAW mavuno mafanikio ya kawaida ya mavuno ya FAW ya mwisho ya misimu mitatu?", "answer": "" }
    ]
  },
  "voice_files": [
    {
      "file": "voice_baffc0d7-3010-42ba-88a2-83693682cc9a_Q1_20251209_111503.wav",
      "survey_id": "baffc0d7-3010-42ba-88a2-83693682cc9a",
      "question_id": "Q1",
      "question": "Unapoteza mavuno kiasi gani kutokana na funza wa jeshi vamizi (FAW)? Tafadhali fikiria misimu mitatu iliyopita. (Asilimia au magunia kwa ekari ni sawa.)",
      "answer": "[BLANK_AUDIO]"
    },
    {
      "file": "voice_baffc0d7-3010-42ba-88a2-83693682cc9a_Q2_20251209_111644.wav",
      "survey_id": "baffc0d7-3010-42ba-88a2-83693682cc9a",
      "question_id": "Q2",
      "question": "Ikiwa ungeweza kuvuna siku 10 mapema, ungekuwa tayari kupunguza mavuno kiasi gani? (Asilimia au magunia kwa ekari.)",
      "answer": "[speaking in foreign language]"
    },
    {
      "file": "voice_baffc0d7-3010-42ba-88a2-83693682cc9a_Q3_20251209_111802.wav",
      "survey_id": "baffc0d7-3010-42ba-88a2-83693682cc9a",
      "question_id": "Q3",
      "question": "Ni kiwango gani cha uharibifu wa wadudu au magonjwa kingekufanya uache kutumia aina yako ya sasa ya mahindi na ubadilishe kwenda aina mpya? (Toa kigezo wazi, kwa mfano: asilimia ya mimea au masikio yaliyoharibika, au kiwango cha ukali.)",
      "answer": "[NON-ENGLISH SPEECH]"
    },
    {
      "file": "voice_baffc0d7-3010-42ba-88a2-83693682cc9a_Q3_20251209_111839.wav",
      "survey_id": "baffc0d7-3010-42ba-88a2-83693682cc9a",
      "question_id": "Q3",
      "question": "Ni kiwango gani cha uharibifu wa wadudu au magonjwa kingekufanya uache kutumia aina yako ya sasa ya mahindi na ubadilishe kwenda aina mpya? (Toa kigezo wazi, kwa mfano: asilimia ya mimea au masikio yaliyoharibika, au kiwango cha ukali.)",
      "answer": "[NON-ENGLISH SPEECH]"
    },
    {
      "file": "voice_baffc0d7-3010-42ba-88a2-83693682cc9a_Q4_20251209_111912.wav",
      "survey_id": "baffc0d7-3010-42ba-88a2-83693682cc9a",
      "question_id": "Q4",
      "question": "Ungetarajia nini kutoka kwa aina mpya ya mahindi ili kuchukua nafasi ya ile unayolima sasa? Tafadhali toa maelezo kwa undani kadiri inavyowezekana (kwa mfano, muda wa kukomaa (DTM), uvumilivu wa FAW, uvumilivu wa ukame katika hatua fulani, mavuno ya kawaida).",
      "answer": "[Spanish]"
    },
    {
      "file": "voice_baffc0d7-3010-42ba-88a2-83693682cc9a_Q4_20251209_111934.wav",
      "survey_id": "baffc0d7-3010-42ba-88a2-83693682cc9a",
      "question_id": "Q4",
      "question": "Ungetarajia nini kutoka kwa aina mpya ya mahindi ili kuchukua nafasi ya ile unayolima sasa? Tafadhali toa maelezo kwa undani kadiri inavyowezekana (kwa mfano, muda wa kukomaa (DTM), uvumilivu wa FAW, uvumilivu wa ukame katika hatua fulani, mavuno ya kawaida).",
      "answer": "[Spanish]"
    },
    {
      "file": "voice_baffc0d7-3010-42ba-88a2-83693682cc9a_Q5_20251209_112231.wav",
      "survey_id": "baffc0d7-3010-42ba-88a2-83693682cc9a",
      "question_id": "Q5",
      "question": "Katika mwaka mbaya, ni mavuno madogo kiasi gani ambayo ungeyakubali na bado ukapande mahindi haya tena msimu unaofuata? (Asilimia ya mavuno ya kawaida au magunia kwa ekari.)",
      "answer": "(speaking in foreign language)"
    },
    {
      "file": "voice_baffc0d7-3010-42ba-88a2-83693682cc9a_Q5_20251209_112341.wav",
      "survey_id": "baffc0d7-3010-42ba-88a2-83693682cc9a",
      "question_id": "Q5",
      "question": "Katika mwaka mbaya, ni mavuno madogo kiasi gani ambayo ungeyakubali na bado ukapande mahindi haya tena msimu unaofuata? (Asilimia ya mavuno ya kawaida au magunia kwa ekari.)",
      "answer": "(speaking in foreign language)"
    },
    {
      "file": "voice_baffc0d7-3010-42ba-88a2-83693682cc9a_Q6_20251209_112518.wav",
      "survey_id": "baffc0d7-3010-42ba-88a2-83693682cc9a",
      "question_id": "Q6",
      "question": "Ni kipindi gani katika msimu ambapo ukame unaathiri mazao yako kwa kiwango kikubwa zaidi? Ni wakati gani wa ukame ambao ni mgumu zaidi kwako? (Kwa mfano, kabla ya kutoa maua, wakati wa kutoa maua/kuchanua, kujaza punje, kabla ya kuvuna.)",
      "answer": "[BLANK_AUDIO]"
    }
  ]
}
